deep_hedging
deep_hedging/base
deep_hedging/config
deep_hedging/curve
deep_hedging/dl
deep_hedging/dl/baselines
deep_hedging/dl/models
deep_hedging/fixed_income
deep_hedging/hedger
deep_hedging/linear
deep_hedging/monte_carlo
deep_hedging/monte_carlo/bid_ask
deep_hedging/monte_carlo/rates
deep_hedging/monte_carlo/spot
deep_hedging/monte_carlo/volatility
deep_hedging/non_linear
deep_hedging/non_linear/exotic
deep_hedging/non_linear/exotic/basket
deep_hedging/non_linear/exotic/two_assets
deep_hedging/non_linear/vanilla
deep_hedging/rl
deep_hedging/underlyings
deep_hedging/utils
